hstsparser.py
hstsparser-1.2.0.dist-info/LICENSE
hstsparser-1.2.0.dist-info/METADATA
hstsparser-1.2.0.dist-info/WHEEL
hstsparser-1.2.0.dist-info/entry_points.txt
hstsparser-1.2.0.dist-info/RECORD
