Metadata-Version: 2.1
Name: hstsparser
Version: 1.2.0
Summary: A tool to parse Firefox and Chrome HSTS databases into forensic artifacts.
Home-page: https://github.com/thebeanogamer/hstsparser
License: MIT
Keywords: chrome,firefox,dfir,forensics,hsts
Author: Daniel Milnes
Author-email: daniel@daniel-milnes.uk
Requires-Python: >=3.9
Classifier: License :: OSI Approved :: MIT License
Classifier: Natural Language :: English
Classifier: Programming Language :: Python :: 3
Classifier: Programming Language :: Python :: 3.9
Classifier: Programming Language :: Python :: 3.10
Classifier: Programming Language :: Python :: 3.11
Classifier: Topic :: Security
Classifier: Topic :: Utilities
Requires-Dist: prettytable (>=0.7.2)
Project-URL: Documentation, https://github.com/thebeanogamer/hstsparser
Project-URL: Repository, https://github.com/thebeanogamer/hstsparser
